{
    "services":[
        {
            "id":1,
            "title":"Carpet cleaning Service",
            "body":"Carpet cleaning service details here...",
            "imageUrl":"/cleaning.jpg"
        },
        {
            "id":2,
            "title":"Deep Cleaning",
            "body":"Deep cleaning service details here... ",
            "price":550,
            "imageUrl":"/deep_cleaning.jpg"
        },
        {
            "id":3,
            "title":"Rug Cleaning",
            "body":"Rug cleaning service details here... ",
            "price":600,
            "imageUrl":"/rug_cleaning.jpg"
        }
    ],
    "blogs":[
        {
        "id":1,
        "title":"First blog title here",
        "body":"First blog body here........"
        },
        {
        "id":2,
        "title":"Second blog title here",
        "body":"Second blog body here........"
        },
        {
        "id":3,
        "title":"Third blog title here",
        "body":"Third blog body here........"
        }
    ]
}